{
  "exam_type": {
    "exam_board": "Pearson Edexcel",
    "exam_level": "GCSE",
    "subject": "Mathematics",
    "paper_code": "1MA1/3H",
    "display_name": "Paper 3 (Calculator)"
  },
  "paper_instance": {
    "exam_date": "2023-11-13",
    "total_marks": 80
  },
  "grade_boundaries": [
    {
      "grade": "9",
      "min_raw_marks": 67,
      "display_order": 1
    },
    {
      "grade": "8",
      "min_raw_marks": 57,
      "display_order": 2
    },
    {
      "grade": "7",
      "min_raw_marks": 48,
      "display_order": 3
    },
    {
      "grade": "6",
      "min_raw_marks": 37,
      "display_order": 4
    },
    {
      "grade": "5",
      "min_raw_marks": 26,
      "display_order": 5
    },
    {
      "grade": "4",
      "min_raw_marks": 15,
      "display_order": 6
    },
    {
      "grade": "3",
      "min_raw_marks": 9,
      "display_order": 7
    }
  ],
  "questions": [
    {
      "question_number": 1,
      "total_marks": 2,
      "parts": [
        {
          "part_letter": null,
          "sub_part_letter": null,
          "display_order": 0,
          "content_blocks": []
        },
        {
          "part_letter": "a",
          "sub_part_letter": null,
          "display_order": 1,
          "content_blocks": [
            {
              "block_type": "text",
              "display_order": 1,
              "content_text": "Write $468000$ in standard form.",
              "diagram_description": null
            }
          ]
        },
        {
          "part_letter": "b",
          "sub_part_letter": null,
          "display_order": 2,
          "content_blocks": [
            {
              "block_type": "text",
              "display_order": 1,
              "content_text": "Write $5.037 \\times 10^{-4}$ as an ordinary number.",
              "diagram_description": null
            }
          ]
        }
      ]
    },
    {
      "question_number": 2,
      "total_marks": 2,
      "parts": [
        {
          "part_letter": null,
          "sub_part_letter": null,
          "display_order": 0,
          "content_blocks": [
            {
              "block_type": "text",
              "display_order": 1,
              "content_text": "Here is a biased spinner.",
              "diagram_description": null
            },
            {
              "block_type": "diagram",
              "display_order": 2,
              "content_text": null,
              "diagram_description": "A four-section spinner with sections labeled A, D, B, and C arranged around a central point"
            },
            {
              "block_type": "text",
              "display_order": 3,
              "content_text": "The table shows the probabilities that when the spinner is spun it will land on A, on B, on C and on D. Luka will spin the spinner $200$ times. Work out an estimate for the number of times the spinner will land on A.",
              "diagram_description": null
            }
          ]
        }
      ]
    },
    {
      "question_number": 3,
      "total_marks": 4,
      "parts": [
        {
          "part_letter": null,
          "sub_part_letter": null,
          "display_order": 0,
          "content_blocks": [
            {
              "block_type": "text",
              "display_order": 1,
              "content_text": "Seija works at a weather station. The table gives information about the temperature, $T$ \u00b0C, at midday for each of $50$ cities in the UK on Tuesday.",
              "diagram_description": null
            }
          ]
        },
        {
          "part_letter": "a",
          "sub_part_letter": null,
          "display_order": 1,
          "content_blocks": [
            {
              "block_type": "text",
              "display_order": 1,
              "content_text": "Calculate an estimate for the mean temperature.",
              "diagram_description": null
            }
          ]
        },
        {
          "part_letter": "b",
          "sub_part_letter": null,
          "display_order": 2,
          "content_blocks": [
            {
              "block_type": "text",
              "display_order": 1,
              "content_text": "Seija says, \"The median temperature is $22.5$ \u00b0C because $22.5$ is the middle number in the middle group.\" Is Seija correct? Give a reason for your answer.",
              "diagram_description": null
            }
          ]
        }
      ]
    },
    {
      "question_number": 4,
      "total_marks": 4,
      "parts": [
        {
          "part_letter": null,
          "sub_part_letter": null,
          "display_order": 0,
          "content_blocks": [
            {
              "block_type": "text",
              "display_order": 1,
              "content_text": "Jenna is asked to show the inequality $-3 < x \\leq 4$ on a number line. Here is her answer.",
              "diagram_description": null
            },
            {
              "block_type": "diagram",
              "display_order": 2,
              "content_text": null,
              "diagram_description": "Number line from $-5$ to $5$ with open circles at $-3$ and $4$"
            }
          ]
        },
        {
          "part_letter": "a",
          "sub_part_letter": null,
          "display_order": 1,
          "content_blocks": [
            {
              "block_type": "text",
              "display_order": 1,
              "content_text": "Write down two mistakes Jenna has made.",
              "diagram_description": null
            }
          ]
        },
        {
          "part_letter": "b",
          "sub_part_letter": null,
          "display_order": 2,
          "content_blocks": [
            {
              "block_type": "text",
              "display_order": 1,
              "content_text": "Work out the greatest integer that satisfies the inequality $5y - 7 < 16$",
              "diagram_description": null
            }
          ]
        }
      ]
    },
    {
      "question_number": 5,
      "total_marks": 3,
      "parts": [
        {
          "part_letter": null,
          "sub_part_letter": null,
          "display_order": 0,
          "content_blocks": [
            {
              "block_type": "text",
              "display_order": 1,
              "content_text": "Ali buys packs of balloons and boxes of pencils. There are $30$ balloons in each pack. There are $24$ pencils in each box. Ali buys exactly the same number of balloons and pencils. Work out how many packs of balloons and how many boxes of pencils she could have bought. You must show all your working.",
              "diagram_description": null
            }
          ]
        }
      ]
    },
    {
      "question_number": 6,
      "total_marks": 2,
      "parts": [
        {
          "part_letter": null,
          "sub_part_letter": null,
          "display_order": 0,
          "content_blocks": [
            {
              "block_type": "text",
              "display_order": 1,
              "content_text": "A company orders a large number of plates from a factory. It would take $30$ hours to make all the plates using $4$ machines. How many machines are needed to make all the plates in $6$ hours?",
              "diagram_description": null
            }
          ]
        }
      ]
    },
    {
      "question_number": 7,
      "total_marks": 3,
      "parts": [
        {
          "part_letter": null,
          "sub_part_letter": null,
          "display_order": 0,
          "content_blocks": [
            {
              "block_type": "text",
              "display_order": 1,
              "content_text": "Riley travelled by car and by aeroplane. He travelled $143$ miles by car at an average speed of $55$ miles per hour. Riley then travelled for $5$ hours and $20$ minutes by aeroplane. Work out, in hours and minutes, Riley's total travelling time.",
              "diagram_description": null
            }
          ]
        }
      ]
    },
    {
      "question_number": 8,
      "total_marks": 3,
      "parts": [
        {
          "part_letter": null,
          "sub_part_letter": null,
          "display_order": 0,
          "content_blocks": [
            {
              "block_type": "text",
              "display_order": 1,
              "content_text": "The diagram shows a solid cube placed on a horizontal table.",
              "diagram_description": null
            },
            {
              "block_type": "diagram",
              "display_order": 2,
              "content_text": null,
              "diagram_description": "A cube shown in 3D perspective with dashed lines for hidden edges, and a formula box showing $\\text{pressure} = \\frac{\\text{force}}{\\text{area}}$"
            },
            {
              "block_type": "text",
              "display_order": 3,
              "content_text": "The pressure on the table due to the cube is $3.5$ newtons/cm$^2$. The force exerted by the cube on the table is $504$ newtons. Show that the total surface area of the cube is less than $900$cm$^2$.",
              "diagram_description": null
            }
          ]
        }
      ]
    },
    {
      "question_number": 9,
      "total_marks": 3,
      "parts": [
        {
          "part_letter": null,
          "sub_part_letter": null,
          "display_order": 0,
          "content_blocks": [
            {
              "block_type": "text",
              "display_order": 1,
              "content_text": "The line $L$ is shown on the grid.",
              "diagram_description": null
            },
            {
              "block_type": "diagram",
              "display_order": 2,
              "content_text": null,
              "diagram_description": "Coordinate grid showing line $L$ passing through points approximately $(-1, 5)$ and $(2, -3)$, with $x$-axis from $-2$ to $4$ and $y$-axis from $-3$ to $5$"
            },
            {
              "block_type": "text",
              "display_order": 3,
              "content_text": "Find an equation for $L$.",
              "diagram_description": null
            }
          ]
        }
      ]
    },
    {
      "question_number": 10,
      "total_marks": 3,
      "parts": [
        {
          "part_letter": null,
          "sub_part_letter": null,
          "display_order": 0,
          "content_blocks": [
            {
              "block_type": "text",
              "display_order": 1,
              "content_text": "Make $m$ the subject of $k = p + \\frac{2m}{5}$",
              "diagram_description": null
            }
          ]
        }
      ]
    },
    {
      "question_number": 11,
      "total_marks": 3,
      "parts": [
        {
          "part_letter": null,
          "sub_part_letter": null,
          "display_order": 0,
          "content_blocks": [
            {
              "block_type": "text",
              "display_order": 1,
              "content_text": "The floor plan of a house is drawn using a scale of $1:50$. On the plan, a room in the house has a floor area of $48$cm$^2$. Work out the real area of the floor of this room. Give your answer in m$^2$.",
              "diagram_description": null
            }
          ]
        }
      ]
    },
    {
      "question_number": 12,
      "total_marks": 2,
      "parts": [
        {
          "part_letter": null,
          "sub_part_letter": null,
          "display_order": 0,
          "content_blocks": [
            {
              "block_type": "text",
              "display_order": 1,
              "content_text": "The diagram shows a shaded sector $POQ$ of a circle with centre $O$ and radius $6.2$ cm.",
              "diagram_description": null
            },
            {
              "block_type": "diagram",
              "display_order": 2,
              "content_text": null,
              "diagram_description": "A shaded circular sector with center $O$, radius $6.2$ cm from $O$ to points $P$ and $Q$, with angle $x$ at the center"
            },
            {
              "block_type": "text",
              "display_order": 3,
              "content_text": "The area of the shaded sector is $82.6$cm$^2$. Calculate the size of angle $x$. Give your answer correct to $3$ significant figures.",
              "diagram_description": null
            }
          ]
        }
      ]
    },
    {
      "question_number": 13,
      "total_marks": 6,
      "parts": [
        {
          "part_letter": null,
          "sub_part_letter": null,
          "display_order": 0,
          "content_blocks": [
            {
              "block_type": "text",
              "display_order": 1,
              "content_text": "Alan grew $80$ plants of the same type outside. The cumulative frequency graph shows information about the heights, in cm, of these plants.",
              "diagram_description": null
            },
            {
              "block_type": "diagram",
              "display_order": 2,
              "content_text": null,
              "diagram_description": "Cumulative frequency graph showing a smooth S-shaped curve, with height (cm) on $x$-axis from $0$ to $125$ and cumulative frequency on $y$-axis from $0$ to $80$"
            },
            {
              "block_type": "text",
              "display_order": 3,
              "content_text": "One of the plants is chosen at random.",
              "diagram_description": null
            }
          ]
        },
        {
          "part_letter": "a",
          "sub_part_letter": null,
          "display_order": 1,
          "content_blocks": [
            {
              "block_type": "text",
              "display_order": 1,
              "content_text": "Find an estimate for the probability that this plant will have a height greater than $90$cm.",
              "diagram_description": null
            }
          ]
        },
        {
          "part_letter": "b",
          "sub_part_letter": null,
          "display_order": 2,
          "content_blocks": [
            {
              "block_type": "text",
              "display_order": 1,
              "content_text": "Use the graph to find an estimate for the median height.",
              "diagram_description": null
            }
          ]
        },
        {
          "part_letter": "c",
          "sub_part_letter": null,
          "display_order": 3,
          "content_blocks": [
            {
              "block_type": "text",
              "display_order": 1,
              "content_text": "Use the graph to find an estimate for the interquartile range of the heights.",
              "diagram_description": null
            }
          ]
        },
        {
          "part_letter": "d",
          "sub_part_letter": null,
          "display_order": 4,
          "content_blocks": [
            {
              "block_type": "text",
              "display_order": 1,
              "content_text": "Alan also grew plants of the same type inside. The interquartile range of the heights of these plants is $30$cm. Give one comparison between the distribution of the heights of the plants grown inside with the distribution of the heights of the plants grown outside.",
              "diagram_description": null
            }
          ]
        }
      ]
    },
    {
      "question_number": 14,
      "total_marks": 2,
      "parts": [
        {
          "part_letter": null,
          "sub_part_letter": null,
          "display_order": 0,
          "content_blocks": [
            {
              "block_type": "text",
              "display_order": 1,
              "content_text": "Here are the first six terms of a quadratic sequence. $5$ $11$ $21$ $35$ $53$ $75$ Find an expression, in terms of $n$, for the $n$th term of this sequence.",
              "diagram_description": null
            }
          ]
        }
      ]
    },
    {
      "question_number": 15,
      "total_marks": 2,
      "parts": [
        {
          "part_letter": null,
          "sub_part_letter": null,
          "display_order": 0,
          "content_blocks": [
            {
              "block_type": "text",
              "display_order": 1,
              "content_text": "The diagram shows triangle $ABC$ and triangle $AED$.",
              "diagram_description": null
            },
            {
              "block_type": "diagram",
              "display_order": 2,
              "content_text": null,
              "diagram_description": "Triangle $ABC$ with base $AC$ measuring 80 cm total, split at point $E$ into $AE = 21.6$ cm and $EC = 58.4$ cm. Point $D$ lies on side $AB$ with $AD = 32$ cm and $DB = 22$ cm. Line segment $DE$ connects these interior points, with $D$ on the left side and $E$ on the base."
            },
            {
              "block_type": "text",
              "display_order": 3,
              "content_text": "Show that triangle $ABC$ and triangle $AED$ are similar.",
              "diagram_description": null
            }
          ]
        }
      ]
    },
    {
      "question_number": 16,
      "total_marks": 3,
      "parts": [
        {
          "part_letter": null,
          "sub_part_letter": null,
          "display_order": 0,
          "content_blocks": [
            {
              "block_type": "text",
              "display_order": 1,
              "content_text": "Zia has to set a $4$-digit security passcode on her phone. Each digit of the passcode is a number from $1$ to $9$. She can use each number more than once. Zia tells her friend Amber that the first digit is a cube number, the second digit is a prime number, the third digit is greater than $6$, the fourth digit is an odd number. The diagram shows one possible $4$-digit passcode.",
              "diagram_description": null
            },
            {
              "block_type": "diagram",
              "display_order": 2,
              "content_text": null,
              "diagram_description": "Four circles in a row containing the digits $1$, $3$, $8$, $3$"
            },
            {
              "block_type": "text",
              "display_order": 3,
              "content_text": "Amber is going to have one attempt at guessing Zia's passcode. Work out the probability that Amber guesses Zia's passcode on the first attempt.",
              "diagram_description": null
            }
          ]
        }
      ]
    },
    {
      "question_number": 17,
      "total_marks": 7,
      "parts": [
        {
          "part_letter": null,
          "sub_part_letter": null,
          "display_order": 0,
          "content_blocks": []
        },
        {
          "part_letter": "a",
          "sub_part_letter": "i",
          "display_order": 1,
          "content_blocks": [
            {
              "block_type": "text",
              "display_order": 1,
              "content_text": "Write $x^2 - 8x + 3$ in the form $(x - a)^2 - b$ where $a$ and $b$ are integers.",
              "diagram_description": null
            }
          ]
        },
        {
          "part_letter": "a",
          "sub_part_letter": "ii",
          "display_order": 2,
          "content_blocks": [
            {
              "block_type": "text",
              "display_order": 1,
              "content_text": "Hence, write down the coordinates of the turning point on the graph of $y = x^2 - 8x + 3$",
              "diagram_description": null
            }
          ]
        },
        {
          "part_letter": "b",
          "sub_part_letter": null,
          "display_order": 3,
          "content_blocks": [
            {
              "block_type": "text",
              "display_order": 1,
              "content_text": "Solve $7x^2 + 8x - 5 = 0$. Give your solutions correct to $3$ significant figures.",
              "diagram_description": null
            }
          ]
        },
        {
          "part_letter": "c",
          "sub_part_letter": null,
          "display_order": 4,
          "content_blocks": [
            {
              "block_type": "text",
              "display_order": 1,
              "content_text": "Alex has to find the solutions of the quadratic equation $3k^2 + 10k - 8 = 0$. Here is his working and answer. $(3k - 2)(k + 4) = 0$ $k = 2$ or $k = -4$ What mistake has Alex made?",
              "diagram_description": null
            }
          ]
        }
      ]
    },
    {
      "question_number": 18,
      "total_marks": 3,
      "parts": [
        {
          "part_letter": null,
          "sub_part_letter": null,
          "display_order": 0,
          "content_blocks": [
            {
              "block_type": "diagram",
              "display_order": 1,
              "content_text": null,
              "diagram_description": "Coordinate grid with $x$-axis from $-8$ to $8$ and $y$-axis from $-10$ to $6$, showing triangle $P$ with vertices approximately at $(-7, 5)$, $(-7, 2)$, and $(-5, 2)$"
            }
          ]
        },
        {
          "part_letter": "a",
          "sub_part_letter": null,
          "display_order": 1,
          "content_blocks": [
            {
              "block_type": "text",
              "display_order": 1,
              "content_text": "Enlarge triangle $P$ by scale factor $-1\\frac{1}{2}$ with centre of enlargement $(-2, -1)$. Label your image $Q$.",
              "diagram_description": null
            }
          ]
        },
        {
          "part_letter": "b",
          "sub_part_letter": null,
          "display_order": 2,
          "content_blocks": [
            {
              "block_type": "text",
              "display_order": 1,
              "content_text": "Triangle $P$ is transformed by a combined transformation of a rotation of $90$\u00b0 anticlockwise about the origin followed by a translation to give triangle $R$. Exactly one vertex of triangle $P$ is invariant under the combined transformation. Find one possible column vector for the translation.",
              "diagram_description": null
            }
          ]
        }
      ]
    },
    {
      "question_number": 19,
      "total_marks": 4,
      "parts": [
        {
          "part_letter": null,
          "sub_part_letter": null,
          "display_order": 0,
          "content_blocks": [
            {
              "block_type": "diagram",
              "display_order": 1,
              "content_text": null,
              "diagram_description": "Frustum of a cone with top diameter $5$ cm, base diameter $24$ cm, and height $5$ cm shown with vertical measurement. Formulas shown: Volume of sphere $= \\frac{4}{3}\\pi r^3$, Volume of cone $= \\frac{1}{3}\\pi r^2 h$"
            },
            {
              "block_type": "text",
              "display_order": 2,
              "content_text": "The diagram above shows a frustum $F$ of a cone. The frustum is made by removing a cone with height $10$cm from a solid cone with height $15$ cm and base diameter $24$cm. The solid $S$ is made by removing $F$ from a solid hemisphere as shown in the diagram below.",
              "diagram_description": null
            },
            {
              "block_type": "diagram",
              "display_order": 3,
              "content_text": null,
              "diagram_description": "Hemisphere with diameter $24$ cm shown with a $5$ cm deep depression at the top representing where the frustum is removed"
            },
            {
              "block_type": "text",
              "display_order": 4,
              "content_text": "The hemisphere has diameter $24$ cm. Calculate the volume of solid $S$. Give your answer correct to $3$ significant figures.",
              "diagram_description": null
            }
          ]
        }
      ]
    },
    {
      "question_number": 20,
      "total_marks": 3,
      "parts": [
        {
          "part_letter": null,
          "sub_part_letter": null,
          "display_order": 0,
          "content_blocks": [
            {
              "block_type": "text",
              "display_order": 1,
              "content_text": "The turning point on the graph of $y = g(x)$ has coordinates $(-3, 6)$.",
              "diagram_description": null
            }
          ]
        },
        {
          "part_letter": "a",
          "sub_part_letter": null,
          "display_order": 1,
          "content_blocks": [
            {
              "block_type": "text",
              "display_order": 1,
              "content_text": "Write down the coordinates of the turning point on the graph of $y = g(x - 7)$",
              "diagram_description": null
            }
          ]
        },
        {
          "part_letter": "b",
          "sub_part_letter": null,
          "display_order": 2,
          "content_blocks": [
            {
              "block_type": "text",
              "display_order": 1,
              "content_text": "The graph of $y = f(x)$ is shown on the grid.",
              "diagram_description": null
            },
            {
              "block_type": "diagram",
              "display_order": 2,
              "content_text": null,
              "diagram_description": "Coordinate grid showing parabola opening downward with vertex approximately at $(-2, 3)$, crossing $x$-axis around $x = -5$ and $x = 1$"
            },
            {
              "block_type": "text",
              "display_order": 3,
              "content_text": "On the grid, sketch the graph of $y = f(-x) + 3$",
              "diagram_description": null
            }
          ]
        }
      ]
    },
    {
      "question_number": 21,
      "total_marks": 4,
      "parts": [
        {
          "part_letter": null,
          "sub_part_letter": null,
          "display_order": 0,
          "content_blocks": [
            {
              "block_type": "diagram",
              "display_order": 1,
              "content_text": null,
              "diagram_description": "Circle with center $O$. Points $A$, $B$, $C$, $D$ on circumference. $AC$ is a diameter. $ADE$ and $BCE$ are straight lines extending outside the circle. Angle at $A$ (inside triangle) is $35$\u00b0. Angle at $E$ (outside circle) is $28$\u00b0"
            },
            {
              "block_type": "text",
              "display_order": 2,
              "content_text": "$A$, $B$, $C$ and $D$ are points on the circumference of a circle, centre $O$. $AC$ is a diameter of the circle. $ADE$ and $BCE$ are straight lines. Work out the size of angle $BDC$. Write down any circle theorems that you use.",
              "diagram_description": null
            }
          ]
        }
      ]
    },
    {
      "question_number": 22,
      "total_marks": 4,
      "parts": [
        {
          "part_letter": null,
          "sub_part_letter": null,
          "display_order": 0,
          "content_blocks": [
            {
              "block_type": "text",
              "display_order": 1,
              "content_text": "Ebony makes some bracelets to sell. The materials to make all the bracelets cost \u00a3$190$, correct to the nearest \u00a3$5$. Ebony sells all the bracelets for a total of \u00a3$875$, correct to the nearest \u00a3$5$. The total time taken to make and sell all these bracelets was $72$ hours, correct to the nearest hour. Ebony uses this method to calculate her hourly rate of pay: Hourly rate of pay $= \\frac{\\text{total selling price} - \\text{total cost of materials}}{\\text{total time taken}}$ The minimum hourly rate of pay for someone of Ebony's age is \u00a3$8.20$. By considering bounds, determine if Ebony's hourly rate of pay was definitely more than \u00a3$8.20$. You must show all your working.",
              "diagram_description": null
            }
          ]
        }
      ]
    },
    {
      "question_number": 23,
      "total_marks": 4,
      "parts": [
        {
          "part_letter": null,
          "sub_part_letter": null,
          "display_order": 0,
          "content_blocks": [
            {
              "block_type": "text",
              "display_order": 1,
              "content_text": "Given that $\\frac{2x^2 + y^2}{4x^2 - y^2} = \\frac{43}{11}$ where $x > 0$ and $y > 0$, find, in its simplest form, the ratio $x:y$",
              "diagram_description": null
            }
          ]
        }
      ]
    },
    {
      "question_number": 24,
      "total_marks": 4,
      "parts": [
        {
          "part_letter": null,
          "sub_part_letter": null,
          "display_order": 0,
          "content_blocks": [
            {
              "block_type": "text",
              "display_order": 1,
              "content_text": "The diagram shows a triangular prism with a horizontal rectangular base $ABCD$.",
              "diagram_description": null
            },
            {
              "block_type": "diagram",
              "display_order": 2,
              "content_text": null,
              "diagram_description": "This is a triangular prism with its rectangular base $ABCD$ lying flat and horizontal on a surface. \u2551 The base vertices are positioned as follows: $A$ (front-left), $B$ (front-right), $C$ (back-right), and $D$ (back-left). \u2551 The prism extends vertically upward from this base, with identical triangular cross-sections along its length from left to right. \u2551\u2551 TRIANGULAR FACES: \u2551 Left triangular face (prominent and visible): Vertices are $A$ (bottom-front), $D$ (bottom-back), and $T$ (apex). Point $T$ is positioned directly above the midpoint of edge $AD$, forming an isosceles triangle. This face is oriented toward the viewer (like the entrance of a tent). \u2551 Right triangular face: Vertices are $B$ (bottom-front), $C$ (back-back), and $X$ (apex). Point $X$ is positioned directly above the midpoint of edge $BC$ (parallel to $T$'s position). This face is oriented away from the viewer and is not visible as a complete face. \u2551\u2551 EDGE VISIBILITY: \u2551 Visible edges (solid lines): Left triangle edges $DA$, $DT$, $TA$; Base edges $DA$, $AB$; Top edge $TX$; Right triangle edge $XB$. \u2551 Hidden edges (dashed lines): Base edges $BC$, $CD$; Right triangle edge $XC$. \u2551 Note: All three hidden edges connect to vertex $C$, which is the only vertex obscured from view at the back-right position. \u2551\u2551 ADDITIONAL CONSTRUCTION: Point $M$ is marked at the midpoint of edge $DA$. A dotted construction line connects $M$ to apex $T$"
            },
            {
              "block_type": "text",
              "display_order": 3,
              "content_text": "$M$ is the midpoint of $AD$. The vertex $T$ of the prism is vertically above $M$. $AB = 14.7$ cm, $BC = 3.8$ cm, $MT = 2.3$ cm. $P$ is the point on $AB$ such that $AP:PB = 5:2$. Calculate the size of the angle between $TP$ and the base $ABCD$ of the prism. Give your answer correct to $1$ decimal place.",
              "diagram_description": null
            }
          ]
        }
      ]
    }
  ]
}
